awaitwhat/.clang-format
awaitwhat/__init__.py
awaitwhat/blocker.py
awaitwhat/dot.py
awaitwhat/gather.py
awaitwhat/graph.py
awaitwhat/helpers.py
awaitwhat/sleep.py
awaitwhat/stack.py
awaitwhat/utils.py
awaitwhat/wait.py
awaitwhat/wait_for.py
awaitwhat/what.c
awaitwhat/_what.cpython-39-darwin.so
awaitwhat/_what.cpython-38-x86_64-linux-gnu.so
awaitwhat/_what.cpython-39-x86_64-linux-gnu.so
awaitwhat/_what.cpython-38-darwin.so
awaitwhat-21.1.dist-info/WHEEL
awaitwhat-21.1.dist-info/METADATA
awaitwhat-21.1.dist-info/RECORD
