Metadata-Version: 2.1
Name: awaitwhat
Version: 21.1
Summary: async/await introspection
Home-page: https://github.com/dimaqq/awaitwhat
License: MIT
Keywords: asyncio
Author: Dima Tisnek
Author-email: dimaqq@gmail.com
Requires-Python: >=3.7,<3.10
Classifier: Development Status :: 3 - Alpha
Classifier: Framework :: AsyncIO
Classifier: License :: OSI Approved :: MIT License
Classifier: Operating System :: MacOS :: MacOS X
Classifier: Operating System :: Microsoft :: Windows
Classifier: Operating System :: POSIX :: Linux
Classifier: Programming Language :: Python :: 3
Classifier: Programming Language :: Python :: 3.6
Classifier: Programming Language :: Python :: 3.7
Classifier: Programming Language :: Python :: 3.8
Classifier: Programming Language :: Python :: 3.9
Classifier: Programming Language :: Python :: Implementation :: CPython
Classifier: Topic :: Software Development :: Debuggers
Project-URL: Documentation, https://github.com/dimaqq/awaitwhat
Project-URL: Repository, https://github.com/dimaqq/awaitwhat
